xmrig/__init__.py
xmrig/api.py
xmrig/db.py
xmrig/exceptions.py
xmrig/manager.py
xmrig/models.py
xmrig_api-0.2.4.dist-info/METADATA
xmrig_api-0.2.4.dist-info/WHEEL
xmrig_api-0.2.4.dist-info/licenses/LICENSE
xmrig_api-0.2.4.dist-info/RECORD
