Metadata-Version: 2.4
Name: xmrig-api
Version: 0.2.4
Summary: Allows interacting with the XMRig API.
Project-URL: Homepage, https://github.com/hreikin/xmrig-api
Project-URL: Issues, https://github.com/hreikin/xmrig-api/issues
Author-email: hreikin <hreikin@gmail.com>
License-File: LICENSE
Classifier: License :: OSI Approved :: MIT License
Classifier: Operating System :: OS Independent
Classifier: Programming Language :: Python :: 3
Requires-Python: >=3.8
Requires-Dist: mkdocs-material
Requires-Dist: mkdocstrings[python]
Requires-Dist: requests
Requires-Dist: sqlalchemy
